LICENSE
MANIFEST.in
README.md
package.json
setup.py
dashxy/Abc.py
dashxy/Bca.py
dashxy/Dashxy.py
dashxy/__init__.py
dashxy/_imports_.py
dashxy/async-Dashxy.js
dashxy/async-Dashxy.js.map
dashxy/dashxy.min.js
dashxy/dashxy.min.js.map
dashxy/metadata.json
dashxy/package-info.json
dashxy.egg-info/PKG-INFO
dashxy.egg-info/SOURCES.txt
dashxy.egg-info/dependency_links.txt
dashxy.egg-info/top_level.txt
tests/test_usage.py