Metadata-Version: 2.1
Name: dashxy
Version: 0.0.1
Summary: Dashxy is a set of beautiful , interactive and efficient dash component with tons of options. It can be used to integrate advance components in your dash application.
Author: Neetish Singh <neetishsingh97@gmail.com>
License: MIT
Classifier: Framework :: Dash
License-File: LICENSE
